.gitignore
.travis.yml
CHANGES.txt
CONTRIBUTORS.txt
LICENSE.txt
README.rst
setup.py
src/collective/__init__.py
src/collective.js.prefixfree.egg-info/PKG-INFO
src/collective.js.prefixfree.egg-info/SOURCES.txt
src/collective.js.prefixfree.egg-info/dependency_links.txt
src/collective.js.prefixfree.egg-info/entry_points.txt
src/collective.js.prefixfree.egg-info/namespace_packages.txt
src/collective.js.prefixfree.egg-info/not-zip-safe
src/collective.js.prefixfree.egg-info/requires.txt
src/collective.js.prefixfree.egg-info/top_level.txt
src/collective/js/__init__.py
src/collective/js/prefixfree/__init__.py
src/collective/js/prefixfree/configure.zcml
src/collective/js/prefixfree/interfaces.py
src/collective/js/prefixfree/testing.py
src/collective/js/prefixfree/testing.zcml
src/collective/js/prefixfree/profiles/default/browserlayer.xml
src/collective/js/prefixfree/profiles/default/jsregistry.xml
src/collective/js/prefixfree/profiles/default/metadata.xml
src/collective/js/prefixfree/profiles/testing/metadata.xml
src/collective/js/prefixfree/static/prefixfree.min.js
src/collective/js/prefixfree/tests/__init__.py
src/collective/js/prefixfree/tests/test_example.py