Metadata-Version: 1.0
Name: collective.js.prefixfree
Version: 1.0
Summary: Lea Verou -prefix-free for Plone
Home-page: https://github.com/gotcha/collective.js.prefixfree
Author: Godefroid Chapelle
Author-email: gotcha@bubblenet.be
License: mit
Platform: UNKNOWN
Classifier: Programming Language :: Python
